ansicolorslib/__init__.py
ansicolorslib/ansicolorslib.py
AnsiColorsLib-1.0.1.dist-info/LICENSE
AnsiColorsLib-1.0.1.dist-info/METADATA
AnsiColorsLib-1.0.1.dist-info/WHEEL
AnsiColorsLib-1.0.1.dist-info/top_level.txt
AnsiColorsLib-1.0.1.dist-info/RECORD
