Metadata-Version: 2.1
Name: AnsiColorsLib
Version: 1.0.1
Summary: A small library containing ansi color functions.
Home-page: https://github.com/RazKissos/ansicolorslib
Author: Raz Kissos
Author-email: kissosrazz@gmail.com
License: UNKNOWN
Project-URL: github, https://github.com/RazKissos/ansicolorslib
Platform: UNKNOWN
Classifier: Programming Language :: Python :: 3
Classifier: License :: OSI Approved :: MIT License
Classifier: Operating System :: OS Independent
Requires-Python: >=3.6
